odoo/addons/l10n_nl_oin/README.rst
odoo/addons/l10n_nl_oin/__init__.py
odoo/addons/l10n_nl_oin/__manifest__.py
odoo/addons/l10n_nl_oin/i18n/l10n_nl_oin.pot
odoo/addons/l10n_nl_oin/i18n/nl.po
odoo/addons/l10n_nl_oin/i18n/nl_NL.po
odoo/addons/l10n_nl_oin/models/__init__.py
odoo/addons/l10n_nl_oin/models/res_partner.py
odoo/addons/l10n_nl_oin/readme/CONTRIBUTORS.rst
odoo/addons/l10n_nl_oin/readme/DESCRIPTION.rst
odoo/addons/l10n_nl_oin/readme/USAGE.rst
odoo/addons/l10n_nl_oin/static/description/icon.png
odoo/addons/l10n_nl_oin/static/description/index.html
odoo/addons/l10n_nl_oin/tests/__init__.py
odoo/addons/l10n_nl_oin/tests/test_l10n_nl_oin.py
odoo/addons/l10n_nl_oin/views/res_partner.xml
odoo14_addon_l10n_nl_oin-14.0.1.0.1.dev8.dist-info/METADATA
odoo14_addon_l10n_nl_oin-14.0.1.0.1.dev8.dist-info/WHEEL
odoo14_addon_l10n_nl_oin-14.0.1.0.1.dev8.dist-info/top_level.txt
odoo14_addon_l10n_nl_oin-14.0.1.0.1.dev8.dist-info/RECORD
